examples/__init__.py
soco_core/__init__.py
soco_core/convertors.py
soco_core/examples.py
soco_core/sentence_splitter.py
soco_core/soco_client.py
soco_core_python-0.14.1.dist-info/METADATA
soco_core_python-0.14.1.dist-info/RECORD
soco_core_python-0.14.1.dist-info/WHEEL
soco_core_python-0.14.1.dist-info/top_level.txt
