Metadata-Version: 2.1
Name: soco-core-python
Version: 0.14.1
Summary: Python SDK for using SOCO platform
Home-page: https://www.soco.ai
Author: tinachez
License: UNKNOWN
Platform: UNKNOWN
Classifier: Programming Language :: Python :: 3
Classifier: License :: Free for non-commercial use
Classifier: Operating System :: OS Independent
Requires-Dist: nltk (>=3.4)
Requires-Dist: tqdm (>=4.32.1)
